mcp_wiki/__init__.py
mcp_wiki/__main__.py
mcp_wiki/server.py
mcp_wiki-0.1.0.dist-info/METADATA
mcp_wiki-0.1.0.dist-info/WHEEL
mcp_wiki-0.1.0.dist-info/entry_points.txt
mcp_wiki-0.1.0.dist-info/RECORD
