Metadata-Version: 2.4
Name: mcp-wiki
Version: 0.1.0
Summary: MCP Server for Wikipedia
Requires-Python: >=3.13
Requires-Dist: beautifulsoup4>=4.12.3
Requires-Dist: html2text>=2024.2.26
Requires-Dist: mcp[cli]>=1.2.0
Requires-Dist: requests>=2.32.3
